README.md
setup.py
Compyler.egg-info/PKG-INFO
Compyler.egg-info/SOURCES.txt
Compyler.egg-info/dependency_links.txt
Compyler.egg-info/entry_points.txt
Compyler.egg-info/not-zip-safe
Compyler.egg-info/requires.txt
Compyler.egg-info/top_level.txt
compyler/__init__.py
compyler/__main__.py
compyler/ast.py
compyler/codegen.py
compyler/error.py
compyler/lexemes.py
compyler/lexer.py
compyler/node.py
compyler/parser.py
compyler/semantics.py
compyler/symtable.py
compyler/tokens.py
compyler/tree.py
compyler/warning.py