Metadata-Version: 2.1
Name: Compyler
Version: 0.4.4
Summary: Compiler for Spring 2019 Compilers Course, implemented in python.Compiles a custom language into a subset of the 6502 opcodes.
Home-page: https://github.com/dgisolfi/Compyler
Author: dgisolfi
License: MIT
Platform: UNKNOWN
